dakb/__init__.py
dakb/admin/__init__.py
dakb/admin/api.py
dakb/admin/websocket.py
dakb/admin/templates/dashboard.html
dakb/admin/templates/login.html
dakb/cli/__init__.py
dakb/config/default.yaml
dakb/db/__init__.py
dakb/db/admin_schemas.py
dakb/db/collections.py
dakb/db/indexes.py
dakb/db/schemas.py
dakb/db/registration_schemas/__init__.py
dakb/db/registration_schemas/registration.py
dakb/db/repositories/__init__.py
dakb/db/repositories/registration.py
dakb/embeddings/__init__.py
dakb/embeddings/embedding_server.py
dakb/embeddings/embedding_service.py
dakb/embeddings/faiss_sync_service.py
dakb/gateway/__init__.py
dakb/gateway/config.py
dakb/gateway/main.py
dakb/gateway/mcp_session.py
dakb/gateway/middleware/__init__.py
dakb/gateway/middleware/auth.py
dakb/gateway/routes/__init__.py
dakb/gateway/routes/aliases.py
dakb/gateway/routes/knowledge.py
dakb/gateway/routes/mcp.py
dakb/gateway/routes/messaging.py
dakb/gateway/routes/moderation.py
dakb/gateway/routes/registration.py
dakb/gateway/routes/sessions.py
dakb/mcp/__init__.py
dakb/mcp/__main__.py
dakb/mcp/handlers.py
dakb/mcp/server.py
dakb/mcp/tools.py
dakb/messaging/__init__.py
dakb/messaging/api.py
dakb/messaging/models.py
dakb/messaging/notifications.py
dakb/messaging/queue.py
dakb/monitoring/__init__.py
dakb/monitoring/health.py
dakb/monitoring/metrics.py
dakb/security/__init__.py
dakb/security/audit.py
dakb/sessions/__init__.py
dakb/sessions/git_context.py
dakb/sessions/handoff.py
dakb/sessions/models.py
dakb/sessions/patch_bundle.py
dakb/sessions/repository.py
dakb_server-1.2.1.dist-info/licenses/LICENSE
packages/dakb_client/dakb_client/__init__.py
packages/dakb_client/dakb_client/async_client.py
packages/dakb_client/dakb_client/client.py
packages/dakb_client/dakb_client/exceptions.py
packages/dakb_client/dakb_client/mcp_client.py
packages/dakb_client/dakb_client/models.py
packages/dakb_client/dakb_client/py.typed
packages/local_proxy/__init__.py
packages/local_proxy/cache.py
packages/local_proxy/cli.py
packages/local_proxy/config.py
dakb_server-1.2.1.dist-info/METADATA
dakb_server-1.2.1.dist-info/WHEEL
dakb_server-1.2.1.dist-info/entry_points.txt
dakb_server-1.2.1.dist-info/top_level.txt
dakb_server-1.2.1.dist-info/RECORD
