Metadata-Version: 2.4
Name: dakb-server
Version: 1.2.1
Summary: Distributed Agent Knowledge Base Server - A shared knowledge system for multi-agent AI collaboration
Author: oracleseed
Maintainer: oracleseed
License-Expression: Apache-2.0
Project-URL: Homepage, https://github.com/oracleseed/dakb
Project-URL: Documentation, https://github.com/oracleseed/dakb#documentation
Project-URL: Repository, https://github.com/oracleseed/dakb
Project-URL: Issues, https://github.com/oracleseed/dakb/issues
Project-URL: Changelog, https://github.com/oracleseed/dakb/blob/main/CHANGELOG.md
Keywords: ai,agents,knowledge-base,multi-agent,llm,claude,mcp,collaboration,semantic-search,faiss,embeddings
Classifier: Development Status :: 4 - Beta
Classifier: Intended Audience :: Developers
Classifier: Operating System :: OS Independent
Classifier: Programming Language :: Python :: 3
Classifier: Programming Language :: Python :: 3.10
Classifier: Programming Language :: Python :: 3.11
Classifier: Programming Language :: Python :: 3.12
Classifier: Topic :: Scientific/Engineering :: Artificial Intelligence
Classifier: Topic :: Software Development :: Libraries :: Python Modules
Classifier: Typing :: Typed
Requires-Python: >=3.10
License-File: LICENSE
Requires-Dist: fastapi>=0.109.0
Requires-Dist: uvicorn[standard]>=0.27.0
Requires-Dist: pymongo>=4.6.0
Requires-Dist: pydantic>=2.5.0
Requires-Dist: pydantic-settings>=2.1.0
Requires-Dist: sentence-transformers>=2.2.0
Requires-Dist: faiss-cpu>=1.7.4
Requires-Dist: numpy>=1.24.0
Requires-Dist: httpx>=0.25.0
Requires-Dist: python-multipart>=0.0.6
Requires-Dist: PyYAML>=6.0
Requires-Dist: python-dotenv>=1.0.0
Requires-Dist: mcp>=1.0.0
Requires-Dist: click>=8.0.0
Provides-Extra: dev
Requires-Dist: pytest>=7.4.0; extra == "dev"
Requires-Dist: pytest-cov>=4.1.0; extra == "dev"
Requires-Dist: pytest-asyncio>=0.21.0; extra == "dev"
Requires-Dist: ruff>=0.1.0; extra == "dev"
Requires-Dist: mypy>=1.7.0; extra == "dev"
Requires-Dist: black>=23.0.0; extra == "dev"
Requires-Dist: isort>=5.12.0; extra == "dev"
Requires-Dist: pre-commit>=3.5.0; extra == "dev"
Requires-Dist: httpx>=0.25.0; extra == "dev"
Provides-Extra: gpu
Requires-Dist: faiss-gpu>=1.7.4; extra == "gpu"
Provides-Extra: docs
Requires-Dist: mkdocs>=1.5.0; extra == "docs"
Requires-Dist: mkdocs-material>=9.0.0; extra == "docs"
Requires-Dist: mkdocstrings[python]>=0.24.0; extra == "docs"
Provides-Extra: all
Requires-Dist: dakb[dev,docs]; extra == "all"
Dynamic: license-file
